[
  [
    {
      "name": "identification.typeOfDeath",
      "type": "text",
      "position": {
        "x": 22,
        "y": 26
      },
      "width": 20,
      "height": 3.92,
      "rotate": 0,
      "alignment": "left",
      "verticalAlignment": "top",
      "fontSize": 9,
      "lineHeight": 1,
      "characterSpacing": 0,
      "fontColor": "#000000",
      "backgroundColor": "",
      "opacity": 1,
      "strikethrough": false,
      "underline": false,
      "required": false,
      "readOnly": false,
      "fontName": "courier",
      "fields": ["identification", "typeOfDeath"]
    },
    {
      "name": "identification.dateOfDeath",
      "type": "text",
      "position": {
        "x": 41.8,
        "y": 26
      },
      "width": 27.53,
      "height": 4.44,
      "rotate": 0,
      "alignment": "left",
      "verticalAlignment": "top",
      "fontSize": 9,
      "lineHeight": 1,
      "characterSpacing": 0,
      "fontColor": "#000000",
      "backgroundColor": "",
      "opacity": 1,
      "strikethrough": false,
      "underline": false,
      "required": false,
      "readOnly": false,
      "fontName": "courier"
    },
    {
      "name": "identification.hourOfDeath",
      "type": "text",
      "position": {
        "x": 71.38,
        "y": 26
      },
      "width": 16.68,
      "height": 4.43,
      "rotate": 0,
      "alignment": "left",
      "verticalAlignment": "top",
      "fontSize": 9,
      "lineHeight": 1,
      "characterSpacing": 0,
      "fontColor": "#000000",
      "backgroundColor": "",
      "opacity": 1,
      "strikethrough": false,
      "underline": false,
      "required": false,
      "readOnly": false,
      "fontName": "courier"
    },
    {
      "name": "identification.susCard",
      "type": "text",
      "position": {
        "x": 92.22,
        "y": 26
      },
      "width": 47.64,
      "height": 4.43,
      "rotate": 0,
      "alignment": "left",
      "verticalAlignment": "top",
      "fontSize": 9,
      "lineHeight": 1,
      "characterSpacing": 0,
      "fontColor": "#000000",
      "backgroundColor": "",
      "opacity": 1,
      "strikethrough": false,
      "underline": false,
      "required": false,
      "readOnly": false,
      "fontName": "courier"
    },
    {
      "name": "identification.naturalness",
      "type": "text",
      "position": {
        "x": 143.76,
        "y": 25
      },
      "width": 48.17,
      "height": 4.96,
      "rotate": 0,
      "alignment": "left",
      "verticalAlignment": "top",
      "fontSize": 9,
      "lineHeight": 1,
      "characterSpacing": 0,
      "fontColor": "#000000",
      "backgroundColor": "",
      "opacity": 1,
      "strikethrough": false,
      "underline": false,
      "required": false,
      "readOnly": false,
      "fontName": "courier"
    },
    {
      "name": "identification.deceasedName",
      "type": "text",
      "position": {
        "x": 22.85,
        "y": 33.5
      },
      "width": 166.7,
      "height": 4.43,
      "rotate": 0,
      "alignment": "left",
      "verticalAlignment": "top",
      "fontSize": 9,
      "lineHeight": 1,
      "characterSpacing": 0,
      "fontColor": "#000000",
      "backgroundColor": "",
      "opacity": 1,
      "strikethrough": false,
      "underline": false,
      "required": false,
      "readOnly": false,
      "fontName": "courier"
    },
    {
      "name": "identification.fathersName",
      "type": "text",
      "position": {
        "x": 23.11,
        "y": 42
      },
      "width": 84.15,
      "height": 4.43,
      "rotate": 0,
      "alignment": "left",
      "verticalAlignment": "top",
      "fontSize": 9,
      "lineHeight": 1,
      "characterSpacing": 0,
      "fontColor": "#000000",
      "backgroundColor": "",
      "opacity": 1,
      "strikethrough": false,
      "underline": false,
      "required": false,
      "readOnly": false,
      "fontName": "courier"
    },
    {
      "name": "identification.mothersName",
      "type": "text",
      "position": {
        "x": 112.48,
        "y": 42
      },
      "width": 78.86,
      "height": 4.43,
      "rotate": 0,
      "alignment": "left",
      "verticalAlignment": "top",
      "fontSize": 9,
      "lineHeight": 1,
      "characterSpacing": 0,
      "fontColor": "#000000",
      "backgroundColor": "",
      "opacity": 1,
      "strikethrough": false,
      "underline": false,
      "required": false,
      "readOnly": false,
      "fontName": "courier"
    },
    {
      "name": "identification.dateOfBirth",
      "type": "text",
      "position": {
        "x": 22.8,
        "y": 52.5
      },
      "width": 22.24,
      "height": 4.43,
      "rotate": 0,
      "alignment": "left",
      "verticalAlignment": "top",
      "fontSize": 9,
      "lineHeight": 1,
      "characterSpacing": 0,
      "fontColor": "#000000",
      "backgroundColor": "",
      "opacity": 1,
      "strikethrough": false,
      "underline": false,
      "required": false,
      "readOnly": false,
      "fontName": "courier"
    },
    {
      "name": "identification.age",
      "type": "text",
      "position": {
        "x": 63.23,
        "y": 52.5
      },
      "width": 50.81,
      "height": 4.43,
      "rotate": 0,
      "alignment": "left",
      "verticalAlignment": "top",
      "fontSize": 9,
      "lineHeight": 1,
      "characterSpacing": 0,
      "fontColor": "#000000",
      "backgroundColor": "",
      "opacity": 1,
      "strikethrough": false,
      "underline": false,
      "required": false,
      "readOnly": false,
      "fontName": "courier"
    },
    {
      "name": "identification.sex",
      "type": "text",
      "position": {
        "x": 116.47,
        "y": 52.5
      },
      "width": 13.24,
      "height": 4.43,
      "rotate": 0,
      "alignment": "center",
      "verticalAlignment": "top",
      "fontSize": 9,
      "lineHeight": 1,
      "characterSpacing": 0,
      "fontColor": "#000000",
      "backgroundColor": "",
      "opacity": 1,
      "strikethrough": false,
      "underline": false,
      "required": false,
      "readOnly": false,
      "fontName": "courier"
    },
    {
      "name": "identification.race",
      "type": "text",
      "position": {
        "x": 132.56,
        "y": 52.5
      },
      "width": 21.7,
      "height": 4.43,
      "rotate": 0,
      "alignment": "left",
      "verticalAlignment": "top",
      "fontSize": 9,
      "lineHeight": 1,
      "characterSpacing": 0,
      "fontColor": "#000000",
      "backgroundColor": "",
      "opacity": 1,
      "strikethrough": false,
      "underline": false,
      "required": false,
      "readOnly": false,
      "fontName": "courier"
    },
    {
      "name": "identification.maritalStatus",
      "type": "text",
      "position": {
        "x": 156.5,
        "y": 52.5
      },
      "width": 34.93,
      "height": 4.43,
      "rotate": 0,
      "alignment": "left",
      "verticalAlignment": "top",
      "fontSize": 9,
      "lineHeight": 1,
      "characterSpacing": 0,
      "fontColor": "#000000",
      "backgroundColor": "",
      "opacity": 1,
      "strikethrough": false,
      "underline": false,
      "required": false,
      "readOnly": false,
      "fontName": "courier"
    },
    {
      "name": "identification.education",
      "type": "text",
      "position": {
        "x": 22,
        "y": 64
      },
      "width": 52.66,
      "height": 4.43,
      "rotate": 0,
      "alignment": "left",
      "verticalAlignment": "top",
      "fontSize": 9,
      "lineHeight": 1,
      "characterSpacing": 0,
      "fontColor": "#000000",
      "backgroundColor": "",
      "opacity": 1,
      "strikethrough": false,
      "underline": false,
      "required": false,
      "readOnly": false,
      "fontName": "courier"
    },
    {
      "name": "identification.class",
      "type": "text",
      "position": {
        "x": 76,
        "y": 64
      },
      "width": 22.22,
      "height": 4.43,
      "rotate": 0,
      "alignment": "left",
      "verticalAlignment": "top",
      "fontSize": 9,
      "lineHeight": 1,
      "characterSpacing": 0,
      "fontColor": "#000000",
      "backgroundColor": "",
      "opacity": 1,
      "strikethrough": false,
      "underline": false,
      "required": false,
      "readOnly": false,
      "fontName": "courier"
    },
    {
      "name": "identification.occupation",
      "type": "text",
      "position": {
        "x": 102.14,
        "y": 64
      },
      "width": 48.42,
      "height": 4.43,
      "rotate": 0,
      "alignment": "left",
      "verticalAlignment": "top",
      "fontSize": 9,
      "lineHeight": 1,
      "characterSpacing": 0,
      "fontColor": "#000000",
      "backgroundColor": "",
      "opacity": 1,
      "strikethrough": false,
      "underline": false,
      "required": false,
      "readOnly": false,
      "fontName": "courier"
    },
    {
      "name": "identification.cbo",
      "type": "text",
      "position": {
        "x": 152.71,
        "y": 64
      },
      "width": 39.42,
      "height": 4.43,
      "rotate": 0,
      "alignment": "left",
      "verticalAlignment": "top",
      "fontSize": 9,
      "lineHeight": 1,
      "characterSpacing": 0,
      "fontColor": "#000000",
      "backgroundColor": "",
      "opacity": 1,
      "strikethrough": false,
      "underline": false,
      "required": false,
      "readOnly": false,
      "fontName": "courier"
    },
    {
      "name": "identification.deceasedAddress.street",
      "type": "text",
      "position": {
        "x": 22.48,
        "y": 72.5
      },
      "width": 92.08,
      "height": 4.43,
      "rotate": 0,
      "alignment": "left",
      "verticalAlignment": "top",
      "fontSize": 9,
      "lineHeight": 1,
      "characterSpacing": 0,
      "fontColor": "#000000",
      "backgroundColor": "",
      "opacity": 1,
      "strikethrough": false,
      "underline": false,
      "required": false,
      "readOnly": false,
      "fontName": "courier"
    },
    {
      "name": "identification.deceasedAddress.number",
      "type": "text",
      "position": {
        "x": 116.19,
        "y": 72.5
      },
      "width": 16.14,
      "height": 4.43,
      "rotate": 0,
      "alignment": "left",
      "verticalAlignment": "top",
      "fontSize": 9,
      "lineHeight": 1,
      "characterSpacing": 0,
      "fontColor": "#000000",
      "backgroundColor": "",
      "opacity": 1,
      "strikethrough": false,
      "underline": false,
      "required": false,
      "readOnly": false,
      "fontName": "courier"
    },
    {
      "name": "identification.deceasedAddress.complement",
      "type": "text",
      "position": {
        "x": 134.65,
        "y": 72.5
      },
      "width": 16.14,
      "height": 4.43,
      "rotate": 0,
      "alignment": "left",
      "verticalAlignment": "top",
      "fontSize": 9,
      "lineHeight": 1,
      "characterSpacing": 0,
      "fontColor": "#000000",
      "backgroundColor": "",
      "opacity": 1,
      "strikethrough": false,
      "underline": false,
      "required": false,
      "readOnly": false,
      "fontName": "courier"
    },
    {
      "name": "identification.deceasedAddress.zipCode",
      "type": "text",
      "position": {
        "x": 154.7,
        "y": 72.5
      },
      "width": 36.25,
      "height": 4.43,
      "rotate": 0,
      "alignment": "left",
      "verticalAlignment": "top",
      "fontSize": 9,
      "lineHeight": 1,
      "characterSpacing": 0,
      "fontColor": "#000000",
      "backgroundColor": "",
      "opacity": 1,
      "strikethrough": false,
      "underline": false,
      "required": false,
      "readOnly": false,
      "fontName": "courier"
    },
    {
      "name": "identification.deceasedAddress.neighborhood",
      "type": "text",
      "position": {
        "x": 23.06,
        "y": 80
      },
      "width": 46.3,
      "height": 4.43,
      "rotate": 0,
      "alignment": "left",
      "verticalAlignment": "top",
      "fontSize": 9,
      "lineHeight": 1,
      "characterSpacing": 0,
      "fontColor": "#000000",
      "backgroundColor": "",
      "opacity": 1,
      "strikethrough": false,
      "underline": false,
      "required": false,
      "readOnly": false,
      "fontName": "courier"
    },
    {
      "name": "identification.deceasedAddress.neighborhoodCode",
      "type": "text",
      "position": {
        "x": 71.69,
        "y": 80
      },
      "width": 12.96,
      "height": 4.43,
      "rotate": 0,
      "alignment": "left",
      "verticalAlignment": "top",
      "fontSize": 9,
      "lineHeight": 1,
      "characterSpacing": 0,
      "fontColor": "#000000",
      "backgroundColor": "",
      "opacity": 1,
      "strikethrough": false,
      "underline": false,
      "required": false,
      "readOnly": false,
      "fontName": "courier"
    },
    {
      "name": "identification.deceasedAddress.city",
      "type": "text",
      "position": {
        "x": 89,
        "y": 80
      },
      "width": 56.88,
      "height": 4.43,
      "rotate": 0,
      "alignment": "left",
      "verticalAlignment": "top",
      "fontSize": 9,
      "lineHeight": 1,
      "characterSpacing": 0,
      "fontColor": "#000000",
      "backgroundColor": "",
      "opacity": 1,
      "strikethrough": false,
      "underline": false,
      "required": false,
      "readOnly": false,
      "fontName": "courier"
    },
    {
      "name": "identification.deceasedAddress.cityCode",
      "type": "text",
      "position": {
        "x": 148.21,
        "y": 80
      },
      "width": 32.01,
      "height": 4.43,
      "rotate": 0,
      "alignment": "left",
      "verticalAlignment": "top",
      "fontSize": 9,
      "lineHeight": 1,
      "characterSpacing": 0,
      "fontColor": "#000000",
      "backgroundColor": "",
      "opacity": 1,
      "strikethrough": false,
      "underline": false,
      "required": false,
      "readOnly": false,
      "fontName": "courier"
    },
    {
      "name": "identification.deceasedAddress.state",
      "type": "text",
      "position": {
        "x": 183.66,
        "y": 80
      },
      "width": 8.18,
      "height": 4.43,
      "rotate": 0,
      "alignment": "left",
      "verticalAlignment": "top",
      "fontSize": 9,
      "lineHeight": 1,
      "characterSpacing": 0,
      "fontColor": "#000000",
      "backgroundColor": "",
      "opacity": 1,
      "strikethrough": false,
      "underline": false,
      "required": false,
      "readOnly": false,
      "fontName": "courier"
    },
    {
      "name": "occurrence.placeType",
      "type": "text",
      "position": {
        "x": 23.27,
        "y": 91
      },
      "width": 52.92,
      "height": 4.43,
      "rotate": 0,
      "alignment": "left",
      "verticalAlignment": "top",
      "fontSize": 9,
      "lineHeight": 1,
      "characterSpacing": 0,
      "fontColor": "#000000",
      "backgroundColor": "",
      "opacity": 1,
      "strikethrough": false,
      "underline": false,
      "required": false,
      "readOnly": false,
      "fontName": "courier"
    },
    {
      "name": "occurrence.establishmentName",
      "type": "text",
      "position": {
        "x": 80.1,
        "y": 91
      },
      "width": 77.79,
      "height": 4.43,
      "rotate": 0,
      "alignment": "left",
      "verticalAlignment": "top",
      "fontSize": 9,
      "lineHeight": 1,
      "characterSpacing": 0,
      "fontColor": "#000000",
      "backgroundColor": "",
      "opacity": 1,
      "strikethrough": false,
      "underline": false,
      "required": false,
      "readOnly": false,
      "fontName": "courier"
    },
    {
      "name": "occurrence.cnes",
      "type": "text",
      "position": {
        "x": 159.7,
        "y": 91
      },
      "width": 31.76,
      "height": 4.69,
      "rotate": 0,
      "alignment": "left",
      "verticalAlignment": "top",
      "fontSize": 9,
      "lineHeight": 1,
      "characterSpacing": 0,
      "fontColor": "#000000",
      "backgroundColor": "",
      "opacity": 1,
      "strikethrough": false,
      "underline": false,
      "required": false,
      "readOnly": false,
      "fontName": "courier"
    },
    {
      "name": "occurrence.hospitalAddress.street",
      "type": "text",
      "position": {
        "x": 22.43,
        "y": 99.7
      },
      "width": 92.08,
      "height": 4.43,
      "rotate": 0,
      "alignment": "left",
      "verticalAlignment": "top",
      "fontSize": 9,
      "lineHeight": 1,
      "characterSpacing": 0,
      "fontColor": "#000000",
      "backgroundColor": "",
      "opacity": 1,
      "strikethrough": false,
      "underline": false,
      "required": false,
      "readOnly": false,
      "fontName": "courier"
    },
    {
      "name": "occurrence.hospitalAddress.number",
      "type": "text",
      "position": {
        "x": 116.14,
        "y": 99.7
      },
      "width": 16.14,
      "height": 4.43,
      "rotate": 0,
      "alignment": "left",
      "verticalAlignment": "top",
      "fontSize": 9,
      "lineHeight": 1,
      "characterSpacing": 0,
      "fontColor": "#000000",
      "backgroundColor": "",
      "opacity": 1,
      "strikethrough": false,
      "underline": false,
      "required": false,
      "readOnly": false,
      "fontName": "courier"
    },
    {
      "name": "occurrence.hospitalAddress.complement",
      "type": "text",
      "position": {
        "x": 134.6,
        "y": 99.7
      },
      "width": 16.14,
      "height": 4.43,
      "rotate": 0,
      "alignment": "left",
      "verticalAlignment": "top",
      "fontSize": 9,
      "lineHeight": 1,
      "characterSpacing": 0,
      "fontColor": "#000000",
      "backgroundColor": "",
      "opacity": 1,
      "strikethrough": false,
      "underline": false,
      "required": false,
      "readOnly": false,
      "fontName": "courier"
    },
    {
      "name": "occurrence.hospitalAddress.zipCode",
      "type": "text",
      "position": {
        "x": 154.03,
        "y": 99.7
      },
      "width": 36.25,
      "height": 4.43,
      "rotate": 0,
      "alignment": "left",
      "verticalAlignment": "top",
      "fontSize": 9,
      "lineHeight": 1,
      "characterSpacing": 0,
      "fontColor": "#000000",
      "backgroundColor": "",
      "opacity": 1,
      "strikethrough": false,
      "underline": false,
      "required": false,
      "readOnly": false,
      "fontName": "courier"
    },
    {
      "name": "occurrence.hospitalAddress.neighborhood",
      "type": "text",
      "position": {
        "x": 23.01,
        "y": 106.7
      },
      "width": 45.77,
      "height": 4.43,
      "rotate": 0,
      "alignment": "left",
      "verticalAlignment": "top",
      "fontSize": 9,
      "lineHeight": 1,
      "characterSpacing": 0,
      "fontColor": "#000000",
      "backgroundColor": "",
      "opacity": 1,
      "strikethrough": false,
      "underline": false,
      "required": false,
      "readOnly": false,
      "fontName": "courier",
      "fields": ["occurrence", "hospitalAddress", "neighborhood"]
    },
    {
      "name": "occurrence.hospitalAddress.neighborhoodCode",
      "type": "text",
      "position": {
        "x": 71.38,
        "y": 107
      },
      "width": 12.7,
      "height": 4.43,
      "rotate": 0,
      "alignment": "left",
      "verticalAlignment": "top",
      "fontSize": 9,
      "lineHeight": 1,
      "characterSpacing": 0,
      "fontColor": "#000000",
      "backgroundColor": "",
      "opacity": 1,
      "strikethrough": false,
      "underline": false,
      "required": false,
      "readOnly": false,
      "fontName": "courier",
      "fields": ["occurrence", "hospitalAddress", "neighborhoodCode"]
    },
    {
      "name": "occurrence.hospitalAddress.city",
      "type": "text",
      "position": {
        "x": 88.95,
        "y": 107
      },
      "width": 56.88,
      "height": 4.43,
      "rotate": 0,
      "alignment": "left",
      "verticalAlignment": "top",
      "fontSize": 9,
      "lineHeight": 1,
      "characterSpacing": 0,
      "fontColor": "#000000",
      "backgroundColor": "",
      "opacity": 1,
      "strikethrough": false,
      "underline": false,
      "required": false,
      "readOnly": false,
      "fontName": "courier",
      "fields": ["occurrence", "hospitalAddress", "city"]
    },
    {
      "name": "occurrence.hospitalAddress.cityCode",
      "type": "text",
      "position": {
        "x": 147.37,
        "y": 107
      },
      "width": 32.8,
      "height": 4.43,
      "rotate": 0,
      "alignment": "left",
      "verticalAlignment": "top",
      "fontSize": 9,
      "lineHeight": 1,
      "characterSpacing": 0,
      "fontColor": "#000000",
      "backgroundColor": "",
      "opacity": 1,
      "strikethrough": false,
      "underline": false,
      "required": false,
      "readOnly": false,
      "fontName": "courier",
      "fields": ["occurrence", "hospitalAddress", "cityCode"]
    },
    {
      "name": "occurrence.hospitalAddress.state",
      "type": "text",
      "position": {
        "x": 183.1,
        "y": 107
      },
      "width": 8.18,
      "height": 4.43,
      "rotate": 0,
      "alignment": "left",
      "verticalAlignment": "top",
      "fontSize": 9,
      "lineHeight": 1,
      "characterSpacing": 0,
      "fontColor": "#000000",
      "backgroundColor": "",
      "opacity": 1,
      "strikethrough": false,
      "underline": false,
      "required": false,
      "readOnly": false,
      "fontName": "courier",
      "fields": ["occurrence", "hospitalAddress", "state"]
    },
    {
      "name": "infant.mothersAge",
      "type": "text",
      "position": {
        "x": 22.17,
        "y": 124
      },
      "width": 8.72,
      "height": 4.43,
      "rotate": 0,
      "alignment": "left",
      "verticalAlignment": "top",
      "fontSize": 9,
      "lineHeight": 1,
      "characterSpacing": 0,
      "fontColor": "#000000",
      "backgroundColor": "",
      "opacity": 1,
      "strikethrough": false,
      "underline": false,
      "required": false,
      "readOnly": false,
      "fontName": "courier",
      "fields": ["infant", "mothersAge"]
    },
    {
      "name": "infant.mothersEducation",
      "type": "text",
      "position": {
        "x": 33.48,
        "y": 124
      },
      "width": 52.12,
      "height": 4.43,
      "rotate": 0,
      "alignment": "left",
      "verticalAlignment": "top",
      "fontSize": 9,
      "lineHeight": 1,
      "characterSpacing": 0,
      "fontColor": "#000000",
      "backgroundColor": "",
      "opacity": 1,
      "strikethrough": false,
      "underline": false,
      "required": false,
      "readOnly": false,
      "fontName": "courier",
      "fields": ["infant", "mothersEducation"]
    },
    {
      "name": "infant.class",
      "type": "text",
      "position": {
        "x": 88.12,
        "y": 124.3
      },
      "width": 25.91,
      "height": 4.43,
      "rotate": 0,
      "alignment": "left",
      "verticalAlignment": "top",
      "fontSize": 9,
      "lineHeight": 1,
      "characterSpacing": 0,
      "fontColor": "#000000",
      "backgroundColor": "",
      "opacity": 1,
      "strikethrough": false,
      "underline": false,
      "required": false,
      "readOnly": false,
      "fontName": "courier",
      "fields": ["infant", "class"]
    },
    {
      "name": "infant.mothersOccupation",
      "type": "text",
      "position": {
        "x": 116.91,
        "y": 124.3
      },
      "width": 48.4,
      "height": 4.43,
      "rotate": 0,
      "alignment": "left",
      "verticalAlignment": "top",
      "fontSize": 9,
      "lineHeight": 1,
      "characterSpacing": 0,
      "fontColor": "#000000",
      "backgroundColor": "",
      "opacity": 1,
      "strikethrough": false,
      "underline": false,
      "required": false,
      "readOnly": false,
      "fontName": "courier",
      "fields": ["infant", "mothersOccupation"]
    },
    {
      "name": "infant.mothersCBO",
      "type": "text",
      "position": {
        "x": 168.08,
        "y": 124.3
      },
      "width": 22.99,
      "height": 4.43,
      "rotate": 0,
      "alignment": "left",
      "verticalAlignment": "top",
      "fontSize": 9,
      "lineHeight": 1,
      "characterSpacing": 0,
      "fontColor": "#000000",
      "backgroundColor": "",
      "opacity": 1,
      "strikethrough": false,
      "underline": false,
      "required": false,
      "readOnly": false,
      "fontName": "courier",
      "fields": ["infant", "mothersCBO"]
    },
    {
      "name": "infant.bornAlive",
      "type": "text",
      "position": {
        "x": 22.04,
        "y": 142
      },
      "width": 13.2,
      "height": 4.43,
      "rotate": 0,
      "alignment": "left",
      "verticalAlignment": "top",
      "fontSize": 9,
      "lineHeight": 1,
      "characterSpacing": 0,
      "fontColor": "#000000",
      "backgroundColor": "",
      "opacity": 1,
      "strikethrough": false,
      "underline": false,
      "required": false,
      "readOnly": false,
      "fontName": "courier",
      "fields": ["infant", "bornAlive"]
    },
    {
      "name": "infant.fetalLoss",
      "type": "text",
      "position": {
        "x": 36.27,
        "y": 142
      },
      "width": 12.66,
      "height": 4.43,
      "rotate": 0,
      "alignment": "left",
      "verticalAlignment": "top",
      "fontSize": 9,
      "lineHeight": 1,
      "characterSpacing": 0,
      "fontColor": "#000000",
      "backgroundColor": "",
      "opacity": 1,
      "strikethrough": false,
      "underline": false,
      "required": false,
      "readOnly": false,
      "fontName": "courier",
      "fields": ["infant", "fetalLoss"]
    },
    {
      "name": "infant.weeksPregnant",
      "type": "text",
      "position": {
        "x": 50.51,
        "y": 142
      },
      "width": 17.16,
      "height": 4.43,
      "rotate": 0,
      "alignment": "left",
      "verticalAlignment": "top",
      "fontSize": 9,
      "lineHeight": 1,
      "characterSpacing": 0,
      "fontColor": "#000000",
      "backgroundColor": "",
      "opacity": 1,
      "strikethrough": false,
      "underline": false,
      "required": false,
      "readOnly": false,
      "fontName": "courier",
      "fields": ["infant", "weeksPregnant"]
    },
    {
      "name": "infant.pregnancyType",
      "type": "text",
      "position": {
        "x": 70.31,
        "y": 142
      },
      "width": 17.68,
      "height": 4.43,
      "rotate": 0,
      "alignment": "left",
      "verticalAlignment": "top",
      "fontSize": 9,
      "lineHeight": 1,
      "characterSpacing": 0,
      "fontColor": "#000000",
      "backgroundColor": "",
      "opacity": 1,
      "strikethrough": false,
      "underline": false,
      "required": false,
      "readOnly": false,
      "fontName": "courier",
      "fields": ["infant", "pregnancyType"]
    },
    {
      "name": "infant.birthType",
      "type": "text",
      "position": {
        "x": 90.63,
        "y": 142
      },
      "width": 17.68,
      "height": 4.43,
      "rotate": 0,
      "alignment": "left",
      "verticalAlignment": "top",
      "fontSize": 9,
      "lineHeight": 1,
      "characterSpacing": 0,
      "fontColor": "#000000",
      "backgroundColor": "",
      "opacity": 1,
      "strikethrough": false,
      "underline": false,
      "required": false,
      "readOnly": false,
      "fontName": "courier",
      "fields": ["infant", "birthType"]
    },
    {
      "name": "infant.deathRelativeToBirth",
      "type": "text",
      "position": {
        "x": 112.54,
        "y": 134.24
      },
      "width": 78.79,
      "height": 4.43,
      "rotate": 0,
      "alignment": "left",
      "verticalAlignment": "top",
      "fontSize": 9,
      "lineHeight": 1,
      "characterSpacing": 0,
      "fontColor": "#000000",
      "backgroundColor": "",
      "opacity": 1,
      "strikethrough": false,
      "underline": false,
      "required": false,
      "readOnly": false,
      "fontName": "courier",
      "fields": ["infant", "deathRelativeToBirth"]
    },
    {
      "name": "infant.birthWeight",
      "type": "text",
      "position": {
        "x": 112.29,
        "y": 142
      },
      "width": 18.46,
      "height": 4.43,
      "rotate": 0,
      "alignment": "left",
      "verticalAlignment": "top",
      "fontSize": 9,
      "lineHeight": 1,
      "characterSpacing": 0,
      "fontColor": "#000000",
      "backgroundColor": "",
      "opacity": 1,
      "strikethrough": false,
      "underline": false,
      "required": false,
      "readOnly": false,
      "fontName": "courier",
      "fields": ["infant", "birthWeight"]
    },
    {
      "name": "infant.birthCertificateNumber",
      "type": "text",
      "position": {
        "x": 138.69,
        "y": 142
      },
      "width": 52.59,
      "height": 4.43,
      "rotate": 0,
      "alignment": "left",
      "verticalAlignment": "top",
      "fontSize": 9,
      "lineHeight": 1,
      "characterSpacing": 0,
      "fontColor": "#000000",
      "backgroundColor": "",
      "opacity": 1,
      "strikethrough": false,
      "underline": false,
      "required": false,
      "readOnly": false,
      "fontName": "courier",
      "fields": ["infant", "birthCertificateNumber"]
    },
    {
      "name": "conditions.fertileAgeDeath",
      "type": "text",
      "position": {
        "x": 22.33,
        "y": 157
      },
      "width": 99.15,
      "height": 4.43,
      "rotate": 0,
      "alignment": "left",
      "verticalAlignment": "top",
      "fontSize": 9,
      "lineHeight": 1,
      "characterSpacing": 0,
      "fontColor": "#000000",
      "backgroundColor": "",
      "opacity": 1,
      "strikethrough": false,
      "underline": false,
      "required": false,
      "readOnly": false,
      "fontName": "courier",
      "fields": ["conditions", "fertileAgeDeath"]
    },
    {
      "name": "conditions.receivedMedicalAssistance",
      "type": "text",
      "position": {
        "x": 124.73,
        "y": 157
      },
      "width": 32.21,
      "height": 4.43,
      "rotate": 0,
      "alignment": "left",
      "verticalAlignment": "top",
      "fontSize": 9,
      "lineHeight": 1,
      "characterSpacing": 0,
      "fontColor": "#000000",
      "backgroundColor": "",
      "opacity": 1,
      "strikethrough": false,
      "underline": false,
      "required": false,
      "readOnly": false,
      "fontName": "courier",
      "fields": ["conditions", "receivedMedicalAssistance"]
    },
    {
      "name": "conditions.necropsy",
      "type": "text",
      "position": {
        "x": 159.34,
        "y": 157
      },
      "width": 32.21,
      "height": 4.43,
      "rotate": 0,
      "alignment": "left",
      "verticalAlignment": "top",
      "fontSize": 9,
      "lineHeight": 1,
      "characterSpacing": 0,
      "fontColor": "#000000",
      "backgroundColor": "",
      "opacity": 1,
      "strikethrough": false,
      "underline": false,
      "required": false,
      "readOnly": false,
      "fontName": "courier",
      "fields": ["conditions", "necropsy"]
    },
    {
      "name": "conditions.cause1",
      "type": "text",
      "position": {
        "x": 67,
        "y": 167
      },
      "width": 93.06,
      "height": 4.43,
      "rotate": 0,
      "alignment": "left",
      "verticalAlignment": "top",
      "fontSize": 9,
      "lineHeight": 1,
      "characterSpacing": 0,
      "fontColor": "#000000",
      "backgroundColor": "",
      "opacity": 1,
      "strikethrough": false,
      "underline": false,
      "required": false,
      "readOnly": false,
      "fontName": "courier",
      "fields": ["conditions", "cause1"]
    },
    {
      "name": "conditions.cid1",
      "type": "text",
      "position": {
        "x": 178.75,
        "y": 167.75
      },
      "width": 13.13,
      "height": 4.16,
      "rotate": 0,
      "alignment": "left",
      "verticalAlignment": "top",
      "fontSize": 9,
      "lineHeight": 1,
      "characterSpacing": 0,
      "fontColor": "#000000",
      "backgroundColor": "",
      "opacity": 1,
      "strikethrough": false,
      "underline": false,
      "required": false,
      "readOnly": false,
      "fontName": "courier",
      "fields": ["conditions", "cid1"]
    },
    {
      "name": "conditions.evolutionTime1",
      "type": "text",
      "position": {
        "x": 162,
        "y": 167.75
      },
      "width": 14.72,
      "height": 4.16,
      "rotate": 0,
      "alignment": "left",
      "verticalAlignment": "top",
      "fontSize": 9,
      "lineHeight": 1,
      "characterSpacing": 0,
      "fontColor": "#000000",
      "backgroundColor": "",
      "opacity": 1,
      "strikethrough": false,
      "underline": false,
      "required": false,
      "readOnly": false,
      "fontName": "courier",
      "fields": ["conditions", "evolutionTime1"]
    },
    {
      "name": "conditions.cause2",
      "type": "text",
      "position": {
        "x": 67,
        "y": 174.5
      },
      "width": 93.06,
      "height": 4.43,
      "rotate": 0,
      "alignment": "left",
      "verticalAlignment": "top",
      "fontSize": 9,
      "lineHeight": 1,
      "characterSpacing": 0,
      "fontColor": "#000000",
      "backgroundColor": "",
      "opacity": 1,
      "strikethrough": false,
      "underline": false,
      "required": false,
      "readOnly": false,
      "fontName": "courier",
      "fields": ["conditions", "cause2"]
    },
    {
      "name": "conditions.cid2",
      "type": "text",
      "position": {
        "x": 178.75,
        "y": 174.5
      },
      "width": 13.13,
      "height": 4.16,
      "rotate": 0,
      "alignment": "left",
      "verticalAlignment": "top",
      "fontSize": 9,
      "lineHeight": 1,
      "characterSpacing": 0,
      "fontColor": "#000000",
      "backgroundColor": "",
      "opacity": 1,
      "strikethrough": false,
      "underline": false,
      "required": false,
      "readOnly": false,
      "fontName": "courier",
      "fields": ["conditions", "cid2"]
    },
    {
      "name": "conditions.evolutionTime2",
      "type": "text",
      "position": {
        "x": 162,
        "y": 174.5
      },
      "width": 14.72,
      "height": 4.16,
      "rotate": 0,
      "alignment": "left",
      "verticalAlignment": "top",
      "fontSize": 9,
      "lineHeight": 1,
      "characterSpacing": 0,
      "fontColor": "#000000",
      "backgroundColor": "",
      "opacity": 1,
      "strikethrough": false,
      "underline": false,
      "required": false,
      "readOnly": false,
      "fontName": "courier",
      "fields": ["conditions", "evolutionTime2"]
    },
    {
      "name": "conditions.cause3",
      "type": "text",
      "position": {
        "x": 67,
        "y": 182
      },
      "width": 93.06,
      "height": 4.43,
      "rotate": 0,
      "alignment": "left",
      "verticalAlignment": "top",
      "fontSize": 9,
      "lineHeight": 1,
      "characterSpacing": 0,
      "fontColor": "#000000",
      "backgroundColor": "",
      "opacity": 1,
      "strikethrough": false,
      "underline": false,
      "required": false,
      "readOnly": false,
      "fontName": "courier",
      "fields": ["conditions", "cause3"]
    },
    {
      "name": "conditions.cid3",
      "type": "text",
      "position": {
        "x": 178.75,
        "y": 182
      },
      "width": 13.13,
      "height": 4.16,
      "rotate": 0,
      "alignment": "left",
      "verticalAlignment": "top",
      "fontSize": 9,
      "lineHeight": 1,
      "characterSpacing": 0,
      "fontColor": "#000000",
      "backgroundColor": "",
      "opacity": 1,
      "strikethrough": false,
      "underline": false,
      "required": false,
      "readOnly": false,
      "fontName": "courier",
      "fields": ["conditions", "cid3"]
    },
    {
      "name": "conditions.evolutionTime3",
      "type": "text",
      "position": {
        "x": 162,
        "y": 182
      },
      "width": 14.72,
      "height": 4.16,
      "rotate": 0,
      "alignment": "left",
      "verticalAlignment": "top",
      "fontSize": 9,
      "lineHeight": 1,
      "characterSpacing": 0,
      "fontColor": "#000000",
      "backgroundColor": "",
      "opacity": 1,
      "strikethrough": false,
      "underline": false,
      "required": false,
      "readOnly": false,
      "fontName": "courier",
      "fields": ["conditions", "evolutionTime3"]
    },
    {
      "name": "conditions.cause4",
      "type": "text",
      "position": {
        "x": 67,
        "y": 190
      },
      "width": 93.06,
      "height": 4.43,
      "rotate": 0,
      "alignment": "left",
      "verticalAlignment": "top",
      "fontSize": 9,
      "lineHeight": 1,
      "characterSpacing": 0,
      "fontColor": "#000000",
      "backgroundColor": "",
      "opacity": 1,
      "strikethrough": false,
      "underline": false,
      "required": false,
      "readOnly": false,
      "fontName": "courier",
      "fields": ["conditions", "cause4"]
    },
    {
      "name": "conditions.cid4",
      "type": "text",
      "position": {
        "x": 178.75,
        "y": 190
      },
      "width": 13.13,
      "height": 4.16,
      "rotate": 0,
      "alignment": "left",
      "verticalAlignment": "top",
      "fontSize": 9,
      "lineHeight": 1,
      "characterSpacing": 0,
      "fontColor": "#000000",
      "backgroundColor": "",
      "opacity": 1,
      "strikethrough": false,
      "underline": false,
      "required": false,
      "readOnly": false,
      "fontName": "courier",
      "fields": ["conditions", "cid4"]
    },
    {
      "name": "conditions.evolutionTime4",
      "type": "text",
      "position": {
        "x": 162,
        "y": 190
      },
      "width": 14.72,
      "height": 4.16,
      "rotate": 0,
      "alignment": "left",
      "verticalAlignment": "top",
      "fontSize": 9,
      "lineHeight": 1,
      "characterSpacing": 0,
      "fontColor": "#000000",
      "backgroundColor": "",
      "opacity": 1,
      "strikethrough": false,
      "underline": false,
      "required": false,
      "readOnly": false,
      "fontName": "courier",
      "fields": ["conditions", "evolutionTime4"]
    },
    {
      "name": "conditions.cause5",
      "type": "text",
      "position": {
        "x": 67,
        "y": 197.11
      },
      "width": 93.06,
      "height": 4.43,
      "rotate": 0,
      "alignment": "left",
      "verticalAlignment": "top",
      "fontSize": 9,
      "lineHeight": 1,
      "characterSpacing": 0,
      "fontColor": "#000000",
      "backgroundColor": "",
      "opacity": 1,
      "strikethrough": false,
      "underline": false,
      "required": false,
      "readOnly": false,
      "fontName": "courier",
      "fields": ["conditions", "cause5"]
    },
    {
      "name": "conditions.cid5",
      "type": "text",
      "position": {
        "x": 178.75,
        "y": 197.11
      },
      "width": 13.13,
      "height": 4.16,
      "rotate": 0,
      "alignment": "left",
      "verticalAlignment": "top",
      "fontSize": 9,
      "lineHeight": 1,
      "characterSpacing": 0,
      "fontColor": "#000000",
      "backgroundColor": "",
      "opacity": 1,
      "strikethrough": false,
      "underline": false,
      "required": false,
      "readOnly": false,
      "fontName": "courier",
      "fields": ["conditions", "cid5"]
    },
    {
      "name": "conditions.evolutionTime5",
      "type": "text",
      "position": {
        "x": 162,
        "y": 197.11
      },
      "width": 14.72,
      "height": 4.16,
      "rotate": 0,
      "alignment": "left",
      "verticalAlignment": "top",
      "fontSize": 9,
      "lineHeight": 1,
      "characterSpacing": 0,
      "fontColor": "#000000",
      "backgroundColor": "",
      "opacity": 1,
      "strikethrough": false,
      "underline": false,
      "required": false,
      "readOnly": false,
      "fontName": "courier",
      "fields": ["conditions", "evolutionTime5"]
    },
    {
      "name": "conditions.cause6",
      "type": "text",
      "position": {
        "x": 67,
        "y": 203.5
      },
      "width": 93.06,
      "height": 4.43,
      "rotate": 0,
      "alignment": "left",
      "verticalAlignment": "top",
      "fontSize": 9,
      "lineHeight": 1,
      "characterSpacing": 0,
      "fontColor": "#000000",
      "backgroundColor": "",
      "opacity": 1,
      "strikethrough": false,
      "underline": false,
      "required": false,
      "readOnly": false,
      "fontName": "courier",
      "fields": ["conditions", "cause6"]
    },
    {
      "name": "conditions.cid6",
      "type": "text",
      "position": {
        "x": 178.75,
        "y": 203
      },
      "width": 13.13,
      "height": 4.16,
      "rotate": 0,
      "alignment": "left",
      "verticalAlignment": "top",
      "fontSize": 9,
      "lineHeight": 1,
      "characterSpacing": 0,
      "fontColor": "#000000",
      "backgroundColor": "",
      "opacity": 1,
      "strikethrough": false,
      "underline": false,
      "required": false,
      "readOnly": false,
      "fontName": "courier",
      "fields": ["conditions", "cid6"]
    },
    {
      "name": "conditions.evolutionTime6",
      "type": "text",
      "position": {
        "x": 162,
        "y": 203
      },
      "width": 14.72,
      "height": 4.16,
      "rotate": 0,
      "alignment": "left",
      "verticalAlignment": "top",
      "fontSize": 9,
      "lineHeight": 1,
      "characterSpacing": 0,
      "fontColor": "#000000",
      "backgroundColor": "",
      "opacity": 1,
      "strikethrough": false,
      "underline": false,
      "required": false,
      "readOnly": false,
      "fontName": "courier",
      "fields": ["conditions", "evolutionTime6"]
    },
    {
      "name": "doctor.name",
      "type": "text",
      "position": {
        "x": 21.7,
        "y": 212.97
      },
      "width": 73.74,
      "height": 4.43,
      "rotate": 0,
      "alignment": "left",
      "verticalAlignment": "top",
      "fontSize": 9,
      "lineHeight": 1,
      "characterSpacing": 0,
      "fontColor": "#000000",
      "backgroundColor": "",
      "opacity": 1,
      "strikethrough": false,
      "underline": false,
      "required": false,
      "readOnly": false,
      "fontName": "courier",
      "fields": ["doctor", "name"]
    },
    {
      "name": "doctor.crm",
      "type": "text",
      "position": {
        "x": 97.85,
        "y": 213.19
      },
      "width": 17.64,
      "height": 4.43,
      "rotate": 0,
      "alignment": "left",
      "verticalAlignment": "top",
      "fontSize": 9,
      "lineHeight": 1,
      "characterSpacing": 0,
      "fontColor": "#000000",
      "backgroundColor": "",
      "opacity": 1,
      "strikethrough": false,
      "underline": false,
      "required": false,
      "readOnly": false,
      "fontName": "courier",
      "fields": ["doctor", "crm"]
    },
    {
      "name": "doctor.confirmedBy",
      "type": "text",
      "position": {
        "x": 117.64,
        "y": 213.13
      },
      "width": 25.04,
      "height": 4.43,
      "rotate": 0,
      "alignment": "left",
      "verticalAlignment": "top",
      "fontSize": 9,
      "lineHeight": 1,
      "characterSpacing": 0,
      "fontColor": "#000000",
      "backgroundColor": "",
      "opacity": 1,
      "strikethrough": false,
      "underline": false,
      "required": false,
      "readOnly": false,
      "fontName": "courier",
      "fields": ["doctor", "confirmedBy"]
    },
    {
      "name": "doctor.city",
      "type": "text",
      "position": {
        "x": 146.16,
        "y": 213.34
      },
      "width": 37.74,
      "height": 4.43,
      "rotate": 0,
      "alignment": "left",
      "verticalAlignment": "top",
      "fontSize": 9,
      "lineHeight": 1,
      "characterSpacing": 0,
      "fontColor": "#000000",
      "backgroundColor": "",
      "opacity": 1,
      "strikethrough": false,
      "underline": false,
      "required": false,
      "readOnly": false,
      "fontName": "courier",
      "fields": ["doctor", "city"]
    },
    {
      "name": "doctor.state",
      "type": "text",
      "position": {
        "x": 185.47,
        "y": 213.29
      },
      "width": 5.98,
      "height": 4.43,
      "rotate": 0,
      "alignment": "center",
      "verticalAlignment": "top",
      "fontSize": 9,
      "lineHeight": 1,
      "characterSpacing": 0,
      "fontColor": "#000000",
      "backgroundColor": "",
      "opacity": 1,
      "strikethrough": false,
      "underline": false,
      "required": false,
      "readOnly": false,
      "fontName": "courier",
      "fields": ["doctor", "state"]
    },
    {
      "name": "doctor.contact",
      "type": "text",
      "position": {
        "x": 22.02,
        "y": 221.49
      },
      "width": 45.93,
      "height": 4.43,
      "rotate": 0,
      "alignment": "left",
      "verticalAlignment": "top",
      "fontSize": 9,
      "lineHeight": 1,
      "characterSpacing": 0,
      "fontColor": "#000000",
      "backgroundColor": "",
      "opacity": 1,
      "strikethrough": false,
      "underline": false,
      "required": false,
      "readOnly": false,
      "fontName": "courier",
      "fields": ["doctor", "contact"]
    },
    {
      "name": "doctor.confirmationDate",
      "type": "text",
      "position": {
        "x": 71.18,
        "y": 221.7
      },
      "width": 37.19,
      "height": 4.43,
      "rotate": 0,
      "alignment": "left",
      "verticalAlignment": "top",
      "fontSize": 9,
      "lineHeight": 1,
      "characterSpacing": 0,
      "fontColor": "#000000",
      "backgroundColor": "",
      "opacity": 1,
      "strikethrough": false,
      "underline": false,
      "required": false,
      "readOnly": false,
      "fontName": "courier",
      "fields": ["doctor", "confirmationDate"]
    },
    {
      "name": "external.nonNaturalType",
      "type": "text",
      "position": {
        "x": 21.59,
        "y": 234.3
      },
      "width": 75.55,
      "height": 4.43,
      "rotate": 0,
      "alignment": "left",
      "verticalAlignment": "top",
      "fontSize": 9,
      "lineHeight": 1,
      "characterSpacing": 0,
      "fontColor": "#000000",
      "backgroundColor": "",
      "opacity": 1,
      "strikethrough": false,
      "underline": false,
      "required": false,
      "readOnly": false,
      "fontName": "courier",
      "fields": ["external", "nonNaturalType"]
    },
    {
      "name": "external.workplaceAccident",
      "type": "text",
      "position": {
        "x": 100.39,
        "y": 234.51
      },
      "width": 33.21,
      "height": 4.43,
      "rotate": 0,
      "alignment": "left",
      "verticalAlignment": "top",
      "fontSize": 9,
      "lineHeight": 1,
      "characterSpacing": 0,
      "fontColor": "#000000",
      "backgroundColor": "",
      "opacity": 1,
      "strikethrough": false,
      "underline": false,
      "required": false,
      "readOnly": false,
      "fontName": "courier",
      "fields": ["external", "workplaceAccident"]
    },
    {
      "name": "external.informationSource",
      "type": "text",
      "position": {
        "x": 135,
        "y": 234.51
      },
      "width": 56.23,
      "height": 4.43,
      "rotate": 0,
      "alignment": "left",
      "verticalAlignment": "top",
      "fontSize": 9,
      "lineHeight": 1,
      "characterSpacing": 0,
      "fontColor": "#000000",
      "backgroundColor": "",
      "opacity": 1,
      "strikethrough": false,
      "underline": false,
      "required": false,
      "readOnly": false,
      "fontName": "courier",
      "fields": ["external", "informationSource"]
    },
    {
      "name": "external.occurrenceDescription",
      "type": "text",
      "position": {
        "x": 21.8,
        "y": 244.3
      },
      "width": 116.82,
      "height": 4.43,
      "rotate": 0,
      "alignment": "left",
      "verticalAlignment": "top",
      "fontSize": 9,
      "lineHeight": 1,
      "characterSpacing": 0,
      "fontColor": "#000000",
      "backgroundColor": "",
      "opacity": 1,
      "strikethrough": false,
      "underline": false,
      "required": false,
      "readOnly": false,
      "fontName": "courier",
      "fields": ["external", "occurrenceDescription"]
    },
    {
      "name": "external.placeType",
      "type": "text",
      "position": {
        "x": 139.61,
        "y": 244.25
      },
      "width": 51.99,
      "height": 4.43,
      "rotate": 0,
      "alignment": "left",
      "verticalAlignment": "top",
      "fontSize": 9,
      "lineHeight": 1,
      "characterSpacing": 0,
      "fontColor": "#000000",
      "backgroundColor": "",
      "opacity": 1,
      "strikethrough": false,
      "underline": false,
      "required": false,
      "readOnly": false,
      "fontName": "courier",
      "fields": ["external", "placeType"]
    },
    {
      "name": "external.occurrenceAddress.street",
      "type": "text",
      "position": {
        "x": 21.31,
        "y": 253.63
      },
      "width": 82.29,
      "height": 4.43,
      "rotate": 0,
      "alignment": "left",
      "verticalAlignment": "top",
      "fontSize": 9,
      "lineHeight": 1,
      "characterSpacing": 0,
      "fontColor": "#000000",
      "backgroundColor": "",
      "opacity": 1,
      "strikethrough": false,
      "underline": false,
      "required": false,
      "readOnly": false,
      "fontName": "courier",
      "fields": ["external", "occurrenceAddress", "street"]
    },
    {
      "name": "external.occurrenceAddress.number",
      "type": "text",
      "position": {
        "x": 106.14,
        "y": 253.84
      },
      "width": 12.44,
      "height": 4.43,
      "rotate": 0,
      "alignment": "left",
      "verticalAlignment": "top",
      "fontSize": 9,
      "lineHeight": 1,
      "characterSpacing": 0,
      "fontColor": "#000000",
      "backgroundColor": "",
      "opacity": 1,
      "strikethrough": false,
      "underline": false,
      "required": false,
      "readOnly": false,
      "fontName": "courier",
      "fields": ["external", "occurrenceAddress", "number"]
    },
    {
      "name": "external.occurrenceAddress.neighborhood",
      "type": "text",
      "position": {
        "x": 119.95,
        "y": 253.84
      },
      "width": 26.98,
      "height": 4.43,
      "rotate": 0,
      "alignment": "left",
      "verticalAlignment": "top",
      "fontSize": 9,
      "lineHeight": 1,
      "characterSpacing": 0,
      "fontColor": "#000000",
      "backgroundColor": "",
      "opacity": 1,
      "strikethrough": false,
      "underline": false,
      "required": false,
      "readOnly": false,
      "fontName": "courier",
      "fields": ["external", "occurrenceAddress", "neighborhood"]
    },
    {
      "name": "external.occurrenceAddress.city",
      "type": "text",
      "position": {
        "x": 148.54,
        "y": 254.05
      },
      "width": 31.46,
      "height": 4.43,
      "rotate": 0,
      "alignment": "left",
      "verticalAlignment": "top",
      "fontSize": 9,
      "lineHeight": 1,
      "characterSpacing": 0,
      "fontColor": "#000000",
      "backgroundColor": "",
      "opacity": 1,
      "strikethrough": false,
      "underline": false,
      "required": false,
      "readOnly": false,
      "fontName": "courier",
      "fields": ["external", "occurrenceAddress", "city"]
    },
    {
      "name": "external.occurrenceAddress.state",
      "type": "text",
      "position": {
        "x": 183.24,
        "y": 253.72
      },
      "width": 7.56,
      "height": 4.43,
      "rotate": 0,
      "alignment": "center",
      "verticalAlignment": "top",
      "fontSize": 9,
      "lineHeight": 1,
      "characterSpacing": 0,
      "fontColor": "#000000",
      "backgroundColor": "",
      "opacity": 1,
      "strikethrough": false,
      "underline": false,
      "required": false,
      "readOnly": false,
      "fontName": "courier",
      "fields": ["external", "occurrenceAddress", "state"]
    }
  ]
]
